.gitignore
MANIFEST.in
README.rst
setup.cfg
setup.py
collective/__init__.py
collective.portlet.slideshow.egg-info/PKG-INFO
collective.portlet.slideshow.egg-info/SOURCES.txt
collective.portlet.slideshow.egg-info/dependency_links.txt
collective.portlet.slideshow.egg-info/entry_points.txt
collective.portlet.slideshow.egg-info/namespace_packages.txt
collective.portlet.slideshow.egg-info/not-zip-safe
collective.portlet.slideshow.egg-info/paster_plugins.txt
collective.portlet.slideshow.egg-info/requires.txt
collective.portlet.slideshow.egg-info/top_level.txt
collective/portlet/__init__.py
collective/portlet/slideshow/__init__.py
collective/portlet/slideshow/configure.zcml
collective/portlet/slideshow/slideshow.pt
collective/portlet/slideshow/slideshow.py
collective/portlet/slideshow/profiles/default/metadata.xml
collective/portlet/slideshow/profiles/default/portlets.xml
collective/portlet/slideshow/tests/__init__.py
docs/HISTORY.txt