Metadata-Version: 1.1
Name: collective.portlet.slideshow
Version: 0.0.1
Summary: A simple portlet that displays a slideshow.
Home-page: https://github.com/intk/collective.portlet.slideshow
Author: Andre Goncalves
Author-email: andre@intk.com
License: GPL
Download-URL: https://github.com/intk/collective.portlet.slideshow/tarball/0.0.1
Keywords: slideshow
Platform: UNKNOWN
Classifier: Framework :: Plone
Classifier: Programming Language :: Python
